automate_terminal/__init__.py
automate_terminal/api.py
automate_terminal/applescript_service.py
automate_terminal/cli.py
automate_terminal/command_service.py
automate_terminal/models.py
automate_terminal/terminal_service.py
automate_terminal/terminals/__init__.py
automate_terminal/terminals/apple.py
automate_terminal/terminals/base.py
automate_terminal/terminals/ghostty.py
automate_terminal/terminals/guake.py
automate_terminal/terminals/iterm2.py
automate_terminal/terminals/kitty.py
automate_terminal/terminals/tmux.py
automate_terminal/terminals/vscode.py
automate_terminal/terminals/wezterm.py
automate_terminal-0.1.10.dist-info/METADATA
automate_terminal-0.1.10.dist-info/WHEEL
automate_terminal-0.1.10.dist-info/entry_points.txt
automate_terminal-0.1.10.dist-info/licenses/LICENSE
automate_terminal-0.1.10.dist-info/RECORD
